LICENSE.md
MANIFEST.in
README.md
blendscad_convert.py
blendscad_demos.py
setup.cfg
setup.py
BlendSCAD.egg-info/PKG-INFO
BlendSCAD.egg-info/SOURCES.txt
BlendSCAD.egg-info/dependency_links.txt
BlendSCAD.egg-info/top_level.txt
addons/blendscad_toolbar.py
blendscad/__init__.py
blendscad/colors.py
blendscad/core.py
blendscad/impexp.py
blendscad/math.py
blendscad/primitives.py
blendscad/shapes.py
config/startup.blend
config/userpref.blend
examples/ThisFolderContainsPortsOfTheOpenSCADexamples.txt
examples/example001.scad.py
examples/example002.scad.py
examples/example003.scad.py
examples/example004.scad.py
examples/example005.scad.py
examples/example006.scad.py
examples/example007.dxf
examples/example007.scad.py
examples/example011.scad.py
examples/example012.scad.py
examples/example012.stl
examples/example014.scad.py
examples/example016.scad.py
examples/example016.stl
examples/example018.scad.py
examples/example019.scad.py
examples/projection_demo.py
examples/surface.dat
tests/test_group_new.py
tests/test_screw_rotate.py
tests/test_special_variables.py