Metadata-Version: 1.0
Name: BlendSCAD
Version: 20170429.0.0.2
Summary: OpenSCAD-ify Blender
Home-page: https://github.com/3DLIRIOUS/BlendSCAD
Author: 3DLirious
Author-email: 3DLirious@gmail.com
License: GPL-3
Platform: UNKNOWN
